odoo/addons/website_theme_flexible/README.rst
odoo/addons/website_theme_flexible/__init__.py
odoo/addons/website_theme_flexible/__manifest__.py
odoo/addons/website_theme_flexible/data/theme_flexible_data.xml
odoo/addons/website_theme_flexible/data/website_data.xml
odoo/addons/website_theme_flexible/models/__init__.py
odoo/addons/website_theme_flexible/models/ir_qweb.py
odoo/addons/website_theme_flexible/models/res_config_settings.py
odoo/addons/website_theme_flexible/models/theme_flexible.py
odoo/addons/website_theme_flexible/models/website.py
odoo/addons/website_theme_flexible/security/ir.model.access.csv
odoo/addons/website_theme_flexible/static/description/icon.png
odoo/addons/website_theme_flexible/static/description/screenshot0.png
odoo/addons/website_theme_flexible/static/description/screenshot1.png
odoo/addons/website_theme_flexible/static/description/screenshot2.png
odoo/addons/website_theme_flexible/static/description/screenshot3.png
odoo/addons/website_theme_flexible/static/description/screenshot4.png
odoo/addons/website_theme_flexible/static/lib/bootstrap-colorpicker/LICENSE
odoo/addons/website_theme_flexible/static/lib/bootstrap-colorpicker/bootstrap-colorpicker.css
odoo/addons/website_theme_flexible/static/lib/bootstrap-colorpicker/bootstrap-colorpicker.js
odoo/addons/website_theme_flexible/static/lib/typeahead/LICENSE
odoo/addons/website_theme_flexible/static/lib/typeahead/typeahead.js
odoo/addons/website_theme_flexible/static/lib/typeahead-bootstrap-css/LICENSE
odoo/addons/website_theme_flexible/static/lib/typeahead-bootstrap-css/typeaheadjs.css
odoo/addons/website_theme_flexible/static/src/css/theme_customize.css
odoo/addons/website_theme_flexible/static/src/css/website_theme_flexible.editor.css
odoo/addons/website_theme_flexible/static/src/css/website_theme_flexible.frontend.css
odoo/addons/website_theme_flexible/static/src/js/theme_customize.js
odoo11_addon_website_theme_flexible-11.0.1.0.0.dist-info/DESCRIPTION.rst
odoo11_addon_website_theme_flexible-11.0.1.0.0.dist-info/METADATA
odoo11_addon_website_theme_flexible-11.0.1.0.0.dist-info/RECORD
odoo11_addon_website_theme_flexible-11.0.1.0.0.dist-info/WHEEL
odoo11_addon_website_theme_flexible-11.0.1.0.0.dist-info/metadata.json
odoo11_addon_website_theme_flexible-11.0.1.0.0.dist-info/top_level.txt
